texter/__init__.py
samirtexter-1.1.1.dist-info/METADATA
samirtexter-1.1.1.dist-info/WHEEL
samirtexter-1.1.1.dist-info/top_level.txt
samirtexter-1.1.1.dist-info/RECORD
