Metadata-Version: 2.4
Name: SAMIRTextEr
Version: 1.1.1
Summary: Ein Modul zur korrigierung von Deutschen Rechtschreibfehlern.
Author: Samir
Author-email: Samir <schornograph@gmail.com>
License: MIT
Classifier: Programming Language :: Python :: 3
Classifier: License :: OSI Approved :: MIT License
Classifier: Operating System :: OS Independent
Requires-Python: >=3.6
Dynamic: author
Dynamic: requires-python
